<EML xmlns="urn:oasis:names:tc:evs:schema:eml" xmlns:ds="http://www.w3.org/2000/09/xmldsig#" xmlns:kr="http://www.kiesraad.nl/extensions" xmlns:rg="http://www.kiesraad.nl/reportgenerator" xmlns:xal="urn:oasis:names:tc:ciq:xsdschema:xAL:2.0" xmlns:xnl="urn:oasis:names:tc:ciq:xsdschema:xNL:2.0" xmlns:xsi="http://www.w3.org/2001/XMLSchema-instance" Id="520" SchemaVersion="5" xsi:schemaLocation="urn:oasis:names:tc:evs:schema:eml 520-result-v5-0.xsd http://www.kiesraad.nl/extensions kiesraad-eml-extensions.xsd"><!--Created by: Ondersteunende Software Verkiezingen by IVU Traffic Technologies AG, program: P5, version: 2.11.5--><TransactionId>1</TransactionId><ManagingAuthority><AuthorityIdentifier Id="CSB">Eemsmond</AuthorityIdentifier><AuthorityAddress></AuthorityAddress></ManagingAuthority><kr:CreationDateTime>2014-03-20T00:35:36.372</kr:CreationDateTime><ds:CanonicalizationMethod Algorithm="http://www.w3.org/TR/2001/REC-xml-c14n-20010315#WithComments"></ds:CanonicalizationMethod><Result><Election><ElectionIdentifier Id="GR2014_Eemsmond"><ElectionName>Gemeenteraad Eemsmond 2014</ElectionName><ElectionCategory>GR</ElectionCategory><kr:ElectionSubcategory>GR1</kr:ElectionSubcategory><kr:ElectionDomain Id="1651">Eemsmond</kr:ElectionDomain><kr:ElectionDate>2014-03-19</kr:ElectionDate></ElectionIdentifier><Contest><ContestIdentifier Id="geen"></ContestIdentifier><Selection><AffiliationIdentifier Id="1"><RegisteredName>Partij van de Arbeid (P.v.d.A.)</RegisteredName></AffiliationIdentifier><Elected>yes</Elected></Selection><Selection><Candidate><CandidateIdentifier Id="1"></CandidateIdentifier><CandidateFullName><xnl:PersonName><xnl:NameLine NameType="Initials">A.J.</xnl:NameLine><xnl:FirstName>Ab</xnl:FirstName><xnl:LastName>Slagter</xnl:LastName></xnl:PersonName></CandidateFullName><Gender>male</Gender><QualifyingAddress><xal:Locality><xal:LocalityName>Uithuizermeeden</xal:LocalityName></xal:Locality></QualifyingAddress></Candidate><Ranking>1</Ranking><Elected>yes</Elected></Selection><Selection><Candidate><CandidateIdentifier Id="2"></CandidateIdentifier><CandidateFullName><xnl:PersonName><xnl:NameLine NameType="Initials">H.W.</xnl:NameLine><xnl:FirstName>Lya</xnl:FirstName><xnl:LastName>Groenewoud</xnl:LastName></xnl:PersonName></CandidateFullName><Gender>female</Gender><QualifyingAddress><xal:Locality><xal:LocalityName>Uithuizen</xal:LocalityName></xal:Locality></QualifyingAddress></Candidate><Ranking>2</Ranking><Elected>yes</Elected></Selection><Selection><AffiliationIdentifier Id="2"><RegisteredName>Gemeentebelangen Eemsmond</RegisteredName></AffiliationIdentifier><Elected>yes</Elected></Selection><Selection><Candidate><CandidateIdentifier Id="1"></CandidateIdentifier><CandidateFullName><xnl:PersonName><xnl:NameLine NameType="Initials">H.K.</xnl:NameLine><xnl:FirstName>Harald</xnl:FirstName><xnl:LastName>Bouman</xnl:LastName></xnl:PersonName></CandidateFullName><Gender>male</Gender><QualifyingAddress><xal:Locality><xal:LocalityName>Uithuizen</xal:LocalityName></xal:Locality></QualifyingAddress></Candidate><Ranking>1</Ranking><Elected>yes</Elected></Selection><Selection><Candidate><CandidateIdentifier Id="2"></CandidateIdentifier><CandidateFullName><xnl:PersonName><xnl:NameLine NameType="Initials">R.R.</xnl:NameLine><xnl:FirstName>Rein</xnl:FirstName><xnl:LastName>Eisinga</xnl:LastName></xnl:PersonName></CandidateFullName><Gender>male</Gender><QualifyingAddress><xal:Locality><xal:LocalityName>Stitswerd</xal:LocalityName></xal:Locality></QualifyingAddress></Candidate><Ranking>2</Ranking><Elected>yes</Elected></Selection><Selection><Candidate><CandidateIdentifier Id="3"></CandidateIdentifier><CandidateFullName><xnl:PersonName><xnl:NameLine NameType="Initials">E.</xnl:NameLine><xnl:FirstName>Eltjo</xnl:FirstName><xnl:LastName>Dijkhuis</xnl:LastName></xnl:PersonName></CandidateFullName><Gender>male</Gender><QualifyingAddress><xal:Locality><xal:LocalityName>Uithuizen</xal:LocalityName></xal:Locality></QualifyingAddress></Candidate><Ranking>2</Ranking><Elected>yes</Elected></Selection><Selection><Candidate><CandidateIdentifier Id="4"></CandidateIdentifier><CandidateFullName><xnl:PersonName><xnl:NameLine NameType="Initials">M.R.G.G.</xnl:NameLine><xnl:FirstName>Rose-Marie</xnl:FirstName><xnl:LastName>Zuidema-Verweij</xnl:LastName></xnl:PersonName></CandidateFullName><Gender>female</Gender><QualifyingAddress><xal:Locality><xal:LocalityName>Warffum</xal:LocalityName></xal:Locality></QualifyingAddress></Candidate><Ranking>2</Ranking><Elected>yes</Elected></Selection><Selection><Candidate><CandidateIdentifier Id="5"></CandidateIdentifier><CandidateFullName><xnl:PersonName><xnl:NameLine NameType="Initials">A.</xnl:NameLine><xnl:FirstName>Thijs</xnl:FirstName><xnl:NamePrefix>van</xnl:NamePrefix><xnl:LastName>Kleef</xnl:LastName></xnl:PersonName></CandidateFullName><Gender>male</Gender><QualifyingAddress><xal:Locality><xal:LocalityName>Warffum</xal:LocalityName></xal:Locality></QualifyingAddress></Candidate><Ranking>2</Ranking><Elected>yes</Elected></Selection><Selection><AffiliationIdentifier Id="3"><RegisteredName>CDA</RegisteredName></AffiliationIdentifier><Elected>yes</Elected></Selection><Selection><Candidate><CandidateIdentifier Id="1"></CandidateIdentifier><CandidateFullName><xnl:PersonName><xnl:NameLine NameType="Initials">A.</xnl:NameLine><xnl:FirstName>Alie</xnl:FirstName><xnl:LastName>Spijk-van de Pol</xnl:LastName></xnl:PersonName></CandidateFullName><Gender>female</Gender><QualifyingAddress><xal:Locality><xal:LocalityName>Roodeschool</xal:LocalityName></xal:Locality></QualifyingAddress></Candidate><Ranking>1</Ranking><Elected>yes</Elected></Selection><Selection><Candidate><CandidateIdentifier Id="2"></CandidateIdentifier><CandidateFullName><xnl:PersonName><xnl:NameLine NameType="Initials">H.G.A.</xnl:NameLine><xnl:FirstName>Harrie</xnl:FirstName><xnl:LastName>Sienot</xnl:LastName></xnl:PersonName></CandidateFullName><Gender>male</Gender><QualifyingAddress><xal:Locality><xal:LocalityName>Uithuizen</xal:LocalityName></xal:Locality></QualifyingAddress></Candidate><Ranking>2</Ranking><Elected>yes</Elected></Selection><Selection><Candidate><CandidateIdentifier Id="3"></CandidateIdentifier><CandidateFullName><xnl:PersonName><xnl:NameLine NameType="Initials">G.J.</xnl:NameLine><xnl:FirstName>Jan</xnl:FirstName><xnl:NamePrefix>van de</xnl:NamePrefix><xnl:LastName>Wal</xnl:LastName></xnl:PersonName></CandidateFullName><Gender>male</Gender><QualifyingAddress><xal:Locality><xal:LocalityName>Uithuizermeeden</xal:LocalityName></xal:Locality></QualifyingAddress></Candidate><Ranking>2</Ranking><Elected>yes</Elected></Selection><Selection><AffiliationIdentifier Id="4"><RegisteredName>ChristenUnie</RegisteredName></AffiliationIdentifier><Elected>yes</Elected></Selection><Selection><Candidate><CandidateIdentifier Id="1"></CandidateIdentifier><CandidateFullName><xnl:PersonName><xnl:NameLine NameType="Initials">L.</xnl:NameLine><xnl:FirstName>Bert</xnl:FirstName><xnl:LastName>Rozema</xnl:LastName></xnl:PersonName></CandidateFullName><Gender>male</Gender><QualifyingAddress><xal:Locality><xal:LocalityName>Uithuizen</xal:LocalityName></xal:Locality></QualifyingAddress></Candidate><Ranking>1</Ranking><Elected>yes</Elected></Selection><Selection><Candidate><CandidateIdentifier Id="2"></CandidateIdentifier><CandidateFullName><xnl:PersonName><xnl:NameLine NameType="Initials">H.</xnl:NameLine><xnl:FirstName>Harry</xnl:FirstName><xnl:LastName>Woltjer</xnl:LastName></xnl:PersonName></CandidateFullName><Gender>male</Gender><QualifyingAddress><xal:Locality><xal:LocalityName>Uithuizermeeden</xal:LocalityName></xal:Locality></QualifyingAddress></Candidate><Ranking>2</Ranking><Elected>yes</Elected></Selection><Selection><AffiliationIdentifier Id="6"><RegisteredName>VVD</RegisteredName></AffiliationIdentifier><Elected>yes</Elected></Selection><Selection><Candidate><CandidateIdentifier Id="1"></CandidateIdentifier><CandidateFullName><xnl:PersonName><xnl:NameLine NameType="Initials">L.</xnl:NameLine><xnl:FirstName>Lammert</xnl:FirstName><xnl:LastName>Westerhuis</xnl:LastName></xnl:PersonName></CandidateFullName><Gender>male</Gender><QualifyingAddress><xal:Locality><xal:LocalityName>Usquert</xal:LocalityName></xal:Locality></QualifyingAddress></Candidate><Ranking>2</Ranking><Elected>yes</Elected></Selection><Selection><AffiliationIdentifier Id="7"><RegisteredName>Democraten 66 (D66)</RegisteredName></AffiliationIdentifier><Elected>yes</Elected></Selection><Selection><Candidate><CandidateIdentifier Id="1"></CandidateIdentifier><CandidateFullName><xnl:PersonName><xnl:NameLine NameType="Initials">P.H.</xnl:NameLine><xnl:FirstName>Peter</xnl:FirstName><xnl:NamePrefix>op 't</xnl:NamePrefix><xnl:LastName>Holt</xnl:LastName></xnl:PersonName></CandidateFullName><Gender>male</Gender><QualifyingAddress><xal:Locality><xal:LocalityName>Stitswerd</xal:LocalityName></xal:Locality></QualifyingAddress></Candidate><Ranking>1</Ranking><Elected>yes</Elected></Selection><Selection><AffiliationIdentifier Id="8"><RegisteredName>SP (Socialistische Partij)</RegisteredName></AffiliationIdentifier><Elected>yes</Elected></Selection><Selection><Candidate><CandidateIdentifier Id="1"></CandidateIdentifier><CandidateFullName><xnl:PersonName><xnl:NameLine NameType="Initials">S.W.G.</xnl:NameLine><xnl:FirstName>Sandra</xnl:FirstName><xnl:LastName>Herkströter-van Oijen</xnl:LastName></xnl:PersonName></CandidateFullName><Gender>female</Gender><QualifyingAddress><xal:Locality><xal:LocalityName>Warffum</xal:LocalityName></xal:Locality></QualifyingAddress></Candidate><Ranking>1</Ranking><Elected>yes</Elected></Selection><Selection><Candidate><CandidateIdentifier Id="2"></CandidateIdentifier><CandidateFullName><xnl:PersonName><xnl:NameLine NameType="Initials">L.M.</xnl:NameLine><xnl:FirstName>Linda</xnl:FirstName><xnl:LastName>Visser</xnl:LastName></xnl:PersonName></CandidateFullName><Gender>female</Gender><QualifyingAddress><xal:Locality><xal:LocalityName>Kantens</xal:LocalityName></xal:Locality></QualifyingAddress></Candidate><Ranking>2</Ranking><Elected>yes</Elected></Selection><Selection><Candidate><CandidateIdentifier Id="3"></CandidateIdentifier><CandidateFullName><xnl:PersonName><xnl:NameLine NameType="Initials">J.</xnl:NameLine><xnl:FirstName>Jan</xnl:FirstName><xnl:LastName>Schouten</xnl:LastName></xnl:PersonName></CandidateFullName><Gender>male</Gender><QualifyingAddress><xal:Locality><xal:LocalityName>Usquert</xal:LocalityName></xal:Locality></QualifyingAddress></Candidate><Ranking>2</Ranking><Elected>yes</Elected></Selection></Contest></Election></Result></EML>