<EML xmlns="urn:oasis:names:tc:evs:schema:eml" xmlns:ds="http://www.w3.org/2000/09/xmldsig#" xmlns:kr="http://www.kiesraad.nl/extensions" xmlns:xal="urn:oasis:names:tc:ciq:xsdschema:xAL:2.0" xmlns:xnl="urn:oasis:names:tc:ciq:xsdschema:xNL:2.0" Id="520" SchemaVersion="5"><TransactionId>1</TransactionId><ManagingAuthority><AuthorityIdentifier Id="CSB">Roosendaal</AuthorityIdentifier><AuthorityAddress></AuthorityAddress></ManagingAuthority><kr:CreationDateTime>2022-03-17T14:03:45.033</kr:CreationDateTime><ds:CanonicalizationMethod Algorithm="http://www.w3.org/TR/2001/REC-xml-c14n-20010315#WithComments"></ds:CanonicalizationMethod><Result><Election><ElectionIdentifier Id="GR2022_Roosendaal"><ElectionName>Gemeenteraad Roosendaal 2022</ElectionName><ElectionCategory>GR</ElectionCategory><kr:ElectionSubcategory>GR2</kr:ElectionSubcategory><kr:ElectionDomain Id="1674">Roosendaal</kr:ElectionDomain><kr:ElectionDate>2022-03-16</kr:ElectionDate></ElectionIdentifier><Contest><ContestIdentifier Id="geen"></ContestIdentifier><Selection><AffiliationIdentifier Id="1"><RegisteredName>Roosendaalse Lijst</RegisteredName></AffiliationIdentifier><Elected>yes</Elected></Selection><Selection><Candidate><CandidateIdentifier Id="1"></CandidateIdentifier><CandidateFullName><xnl:PersonName><xnl:NameLine NameType="Initials">I.M.</xnl:NameLine><xnl:FirstName>Inge</xnl:FirstName><xnl:NamePrefix></xnl:NamePrefix><xnl:LastName>Raaijmakers</xnl:LastName></xnl:PersonName></CandidateFullName><Gender>female</Gender><QualifyingAddress><xal:Locality><xal:LocalityName>Roosendaal</xal:LocalityName></xal:Locality></QualifyingAddress></Candidate><Ranking>1</Ranking><Elected>yes</Elected></Selection><Selection><Candidate><CandidateIdentifier Id="2"></CandidateIdentifier><CandidateFullName><xnl:PersonName><xnl:NameLine NameType="Initials">J.C.J.M.</xnl:NameLine><xnl:FirstName>Sjef</xnl:FirstName><xnl:NamePrefix>van</xnl:NamePrefix><xnl:LastName>Dorst</xnl:LastName></xnl:PersonName></CandidateFullName><Gender>male</Gender><QualifyingAddress><xal:Locality><xal:LocalityName>Roosendaal</xal:LocalityName></xal:Locality></QualifyingAddress></Candidate><Ranking>1</Ranking><Elected>yes</Elected></Selection><Selection><Candidate><CandidateIdentifier Id="3"></CandidateIdentifier><CandidateFullName><xnl:PersonName><xnl:NameLine NameType="Initials">G.J.H.M.</xnl:NameLine><xnl:FirstName>Gert-Jan</xnl:FirstName><xnl:NamePrefix>van</xnl:NamePrefix><xnl:LastName>Oosterbosch</xnl:LastName></xnl:PersonName></CandidateFullName><Gender>male</Gender><QualifyingAddress><xal:Locality><xal:LocalityName>Roosendaal</xal:LocalityName></xal:Locality></QualifyingAddress></Candidate><Ranking>1</Ranking><Elected>yes</Elected></Selection><Selection><Candidate><CandidateIdentifier Id="4"></CandidateIdentifier><CandidateFullName><xnl:PersonName><xnl:NameLine NameType="Initials">M.C.M.</xnl:NameLine><xnl:FirstName>Marco</xnl:FirstName><xnl:NamePrefix></xnl:NamePrefix><xnl:LastName>Schillemans</xnl:LastName></xnl:PersonName></CandidateFullName><Gender>male</Gender><QualifyingAddress><xal:Locality><xal:LocalityName>Nispen</xal:LocalityName></xal:Locality></QualifyingAddress></Candidate><Ranking>1</Ranking><Elected>yes</Elected></Selection><Selection><Candidate><CandidateIdentifier Id="5"></CandidateIdentifier><CandidateFullName><xnl:PersonName><xnl:NameLine NameType="Initials">R.G.J.</xnl:NameLine><xnl:FirstName>René</xnl:FirstName><xnl:NamePrefix>van</xnl:NamePrefix><xnl:LastName>Broekhoven</xnl:LastName></xnl:PersonName></CandidateFullName><Gender>male</Gender><QualifyingAddress><xal:Locality><xal:LocalityName>Roosendaal</xal:LocalityName></xal:Locality></QualifyingAddress></Candidate><Ranking>1</Ranking><Elected>yes</Elected></Selection><Selection><Candidate><CandidateIdentifier Id="6"></CandidateIdentifier><CandidateFullName><xnl:PersonName><xnl:NameLine NameType="Initials">P.L.F.</xnl:NameLine><xnl:FirstName>Peter</xnl:FirstName><xnl:NamePrefix></xnl:NamePrefix><xnl:LastName>Raijmaekers</xnl:LastName></xnl:PersonName></CandidateFullName><Gender>male</Gender><QualifyingAddress><xal:Locality><xal:LocalityName>Roosendaal</xal:LocalityName></xal:Locality></QualifyingAddress></Candidate><Ranking>2</Ranking><Elected>yes</Elected></Selection><Selection><Candidate><CandidateIdentifier Id="7"></CandidateIdentifier><CandidateFullName><xnl:PersonName><xnl:NameLine NameType="Initials">S.J.C.M.</xnl:NameLine><xnl:FirstName>Stijn</xnl:FirstName><xnl:NamePrefix>Van</xnl:NamePrefix><xnl:LastName>Looveren</xnl:LastName></xnl:PersonName></CandidateFullName><Gender>male</Gender><QualifyingAddress><xal:Locality><xal:LocalityName>Wouwse Plantage</xal:LocalityName></xal:Locality></QualifyingAddress></Candidate><Ranking>2</Ranking><Elected>yes</Elected></Selection><Selection><AffiliationIdentifier Id="2"><RegisteredName>VLP Roosendaal</RegisteredName></AffiliationIdentifier><Elected>yes</Elected></Selection><Selection><Candidate><CandidateIdentifier Id="1"></CandidateIdentifier><CandidateFullName><xnl:PersonName><xnl:NameLine NameType="Initials">A.</xnl:NameLine><xnl:FirstName>Arwen</xnl:FirstName><xnl:NamePrefix>van</xnl:NamePrefix><xnl:LastName>Gestel</xnl:LastName></xnl:PersonName></CandidateFullName><Gender>male</Gender><QualifyingAddress><xal:Locality><xal:LocalityName>Roosendaal</xal:LocalityName></xal:Locality></QualifyingAddress></Candidate><Ranking>1</Ranking><Elected>yes</Elected></Selection><Selection><Candidate><CandidateIdentifier Id="2"></CandidateIdentifier><CandidateFullName><xnl:PersonName><xnl:NameLine NameType="Initials">E.J.C.</xnl:NameLine><xnl:FirstName>Eric</xnl:FirstName><xnl:NamePrefix>de</xnl:NamePrefix><xnl:LastName>Regt</xnl:LastName></xnl:PersonName></CandidateFullName><Gender>male</Gender><QualifyingAddress><xal:Locality><xal:LocalityName>Wouw</xal:LocalityName></xal:Locality></QualifyingAddress></Candidate><Ranking>1</Ranking><Elected>yes</Elected></Selection><Selection><Candidate><CandidateIdentifier Id="3"></CandidateIdentifier><CandidateFullName><xnl:PersonName><xnl:NameLine NameType="Initials">E.G.A.</xnl:NameLine><xnl:FirstName>Evelien</xnl:FirstName><xnl:NamePrefix>van der</xnl:NamePrefix><xnl:LastName>Star-Deijkers</xnl:LastName></xnl:PersonName></CandidateFullName><Gender>female</Gender><QualifyingAddress><xal:Locality><xal:LocalityName>Roosendaal</xal:LocalityName></xal:Locality></QualifyingAddress></Candidate><Ranking>1</Ranking><Elected>yes</Elected></Selection><Selection><Candidate><CandidateIdentifier Id="4"></CandidateIdentifier><CandidateFullName><xnl:PersonName><xnl:NameLine NameType="Initials">W.C.H.</xnl:NameLine><xnl:FirstName>Wilbert</xnl:FirstName><xnl:NamePrefix></xnl:NamePrefix><xnl:LastName>Brouwers</xnl:LastName></xnl:PersonName></CandidateFullName><Gender>male</Gender><QualifyingAddress><xal:Locality><xal:LocalityName>Roosendaal</xal:LocalityName></xal:Locality></QualifyingAddress></Candidate><Ranking>1</Ranking><Elected>yes</Elected></Selection><Selection><Candidate><CandidateIdentifier Id="5"></CandidateIdentifier><CandidateFullName><xnl:PersonName><xnl:NameLine NameType="Initials">G.A.</xnl:NameLine><xnl:FirstName>Gerard</xnl:FirstName><xnl:NamePrefix>van</xnl:NamePrefix><xnl:LastName>Zalinge</xnl:LastName></xnl:PersonName></CandidateFullName><Gender>male</Gender><QualifyingAddress><xal:Locality><xal:LocalityName>Roosendaal</xal:LocalityName></xal:Locality></QualifyingAddress></Candidate><Ranking>1</Ranking><Elected>yes</Elected></Selection><Selection><Candidate><CandidateIdentifier Id="6"></CandidateIdentifier><CandidateFullName><xnl:PersonName><xnl:NameLine NameType="Initials">J.F.A.</xnl:NameLine><xnl:FirstName>Jos</xnl:FirstName><xnl:NamePrefix></xnl:NamePrefix><xnl:LastName>Heeren</xnl:LastName></xnl:PersonName></CandidateFullName><Gender>male</Gender><QualifyingAddress><xal:Locality><xal:LocalityName>Roosendaal</xal:LocalityName></xal:Locality></QualifyingAddress></Candidate><Ranking>1</Ranking><Elected>yes</Elected></Selection><Selection><Candidate><CandidateIdentifier Id="7"></CandidateIdentifier><CandidateFullName><xnl:PersonName><xnl:NameLine NameType="Initials">F.A.C.</xnl:NameLine><xnl:FirstName>Frank</xnl:FirstName><xnl:NamePrefix></xnl:NamePrefix><xnl:LastName>Roks</xnl:LastName></xnl:PersonName></CandidateFullName><Gender>male</Gender><QualifyingAddress><xal:Locality><xal:LocalityName>Roosendaal</xal:LocalityName></xal:Locality></QualifyingAddress></Candidate><Ranking>1</Ranking><Elected>yes</Elected></Selection><Selection><Candidate><CandidateIdentifier Id="8"></CandidateIdentifier><CandidateFullName><xnl:PersonName><xnl:NameLine NameType="Initials">M.W.C.</xnl:NameLine><xnl:FirstName>Martijn</xnl:FirstName><xnl:NamePrefix></xnl:NamePrefix><xnl:LastName>Verbeek</xnl:LastName></xnl:PersonName></CandidateFullName><Gender>male</Gender><QualifyingAddress><xal:Locality><xal:LocalityName>Roosendaal</xal:LocalityName></xal:Locality></QualifyingAddress></Candidate><Ranking>1</Ranking><Elected>yes</Elected></Selection><Selection><Candidate><CandidateIdentifier Id="9"></CandidateIdentifier><CandidateFullName><xnl:PersonName><xnl:NameLine NameType="Initials">K.A.</xnl:NameLine><xnl:FirstName>Alex</xnl:FirstName><xnl:NamePrefix></xnl:NamePrefix><xnl:LastName>Raggers</xnl:LastName></xnl:PersonName></CandidateFullName><Gender>male</Gender><QualifyingAddress><xal:Locality><xal:LocalityName>Roosendaal</xal:LocalityName></xal:Locality></QualifyingAddress></Candidate><Ranking>2</Ranking><Elected>yes</Elected></Selection><Selection><Candidate><CandidateIdentifier Id="10"></CandidateIdentifier><CandidateFullName><xnl:PersonName><xnl:NameLine NameType="Initials">A.C.P.M.</xnl:NameLine><xnl:FirstName>Toon</xnl:FirstName><xnl:NamePrefix></xnl:NamePrefix><xnl:LastName>Jochems</xnl:LastName></xnl:PersonName></CandidateFullName><Gender>male</Gender><QualifyingAddress><xal:Locality><xal:LocalityName>Wouw</xal:LocalityName></xal:Locality></QualifyingAddress></Candidate><Ranking>2</Ranking><Elected>yes</Elected></Selection><Selection><Candidate><CandidateIdentifier Id="11"></CandidateIdentifier><CandidateFullName><xnl:PersonName><xnl:NameLine NameType="Initials">M.G.A.</xnl:NameLine><xnl:FirstName>Richard</xnl:FirstName><xnl:NamePrefix></xnl:NamePrefix><xnl:LastName>Machielsen</xnl:LastName></xnl:PersonName></CandidateFullName><Gender>male</Gender><QualifyingAddress><xal:Locality><xal:LocalityName>Roosendaal</xal:LocalityName></xal:Locality></QualifyingAddress></Candidate><Ranking>2</Ranking><Elected>yes</Elected></Selection><Selection><AffiliationIdentifier Id="3"><RegisteredName>VVD</RegisteredName></AffiliationIdentifier><Elected>yes</Elected></Selection><Selection><Candidate><CandidateIdentifier Id="1"></CandidateIdentifier><CandidateFullName><xnl:PersonName><xnl:NameLine NameType="Initials">S.M.J.</xnl:NameLine><xnl:FirstName>Sanneke</xnl:FirstName><xnl:NamePrefix></xnl:NamePrefix><xnl:LastName>Vermeulen</xnl:LastName></xnl:PersonName></CandidateFullName><Gender>female</Gender><QualifyingAddress><xal:Locality><xal:LocalityName>Roosendaal</xal:LocalityName></xal:Locality></QualifyingAddress></Candidate><Ranking>1</Ranking><Elected>yes</Elected></Selection><Selection><Candidate><CandidateIdentifier Id="2"></CandidateIdentifier><CandidateFullName><xnl:PersonName><xnl:NameLine NameType="Initials">C.F.J.</xnl:NameLine><xnl:FirstName>Kees</xnl:FirstName><xnl:NamePrefix></xnl:NamePrefix><xnl:LastName>Verstraten</xnl:LastName></xnl:PersonName></CandidateFullName><Gender>male</Gender><QualifyingAddress><xal:Locality><xal:LocalityName>Roosendaal</xal:LocalityName></xal:Locality></QualifyingAddress></Candidate><Ranking>1</Ranking><Elected>yes</Elected></Selection><Selection><Candidate><CandidateIdentifier Id="3"></CandidateIdentifier><CandidateFullName><xnl:PersonName><xnl:NameLine NameType="Initials">M.</xnl:NameLine><xnl:FirstName>Martin</xnl:FirstName><xnl:NamePrefix>van der</xnl:NamePrefix><xnl:LastName>Bijl</xnl:LastName></xnl:PersonName></CandidateFullName><Gender>male</Gender><QualifyingAddress><xal:Locality><xal:LocalityName>Roosendaal</xal:LocalityName></xal:Locality></QualifyingAddress></Candidate><Ranking>2</Ranking><Elected>yes</Elected></Selection><Selection><Candidate><CandidateIdentifier Id="4"></CandidateIdentifier><CandidateFullName><xnl:PersonName><xnl:NameLine NameType="Initials">M.</xnl:NameLine><xnl:FirstName>Menno</xnl:FirstName><xnl:NamePrefix></xnl:NamePrefix><xnl:LastName>Nefs</xnl:LastName></xnl:PersonName></CandidateFullName><Gender>male</Gender><QualifyingAddress><xal:Locality><xal:LocalityName>Roosendaal</xal:LocalityName></xal:Locality></QualifyingAddress></Candidate><Ranking>2</Ranking><Elected>yes</Elected></Selection><Selection><AffiliationIdentifier Id="4"><RegisteredName>CDA</RegisteredName></AffiliationIdentifier><Elected>yes</Elected></Selection><Selection><Candidate><CandidateIdentifier Id="1"></CandidateIdentifier><CandidateFullName><xnl:PersonName><xnl:NameLine NameType="Initials">D.C.M.</xnl:NameLine><xnl:FirstName>Nicole</xnl:FirstName><xnl:NamePrefix></xnl:NamePrefix><xnl:LastName>Roeken</xnl:LastName></xnl:PersonName></CandidateFullName><Gender>female</Gender><QualifyingAddress><xal:Locality><xal:LocalityName>Nispen</xal:LocalityName></xal:Locality></QualifyingAddress></Candidate><Ranking>1</Ranking><Elected>yes</Elected></Selection><Selection><Candidate><CandidateIdentifier Id="2"></CandidateIdentifier><CandidateFullName><xnl:PersonName><xnl:NameLine NameType="Initials">M.A.C.M. J.</xnl:NameLine><xnl:FirstName>René</xnl:FirstName><xnl:NamePrefix>van</xnl:NamePrefix><xnl:LastName>Ginderen</xnl:LastName></xnl:PersonName></CandidateFullName><Gender>male</Gender><QualifyingAddress><xal:Locality><xal:LocalityName>Roosendaal</xal:LocalityName></xal:Locality></QualifyingAddress></Candidate><Ranking>1</Ranking><Elected>yes</Elected></Selection><Selection><Candidate><CandidateIdentifier Id="3"></CandidateIdentifier><CandidateFullName><xnl:PersonName><xnl:NameLine NameType="Initials">A.S.</xnl:NameLine><xnl:FirstName>Sebastiaan</xnl:FirstName><xnl:NamePrefix></xnl:NamePrefix><xnl:LastName>Hamans</xnl:LastName></xnl:PersonName></CandidateFullName><Gender>male</Gender><QualifyingAddress><xal:Locality><xal:LocalityName>Roosendaal</xal:LocalityName></xal:Locality></QualifyingAddress></Candidate><Ranking>2</Ranking><Elected>yes</Elected></Selection><Selection><AffiliationIdentifier Id="5"><RegisteredName>GROENLINKS</RegisteredName></AffiliationIdentifier><Elected>yes</Elected></Selection><Selection><Candidate><CandidateIdentifier Id="1"></CandidateIdentifier><CandidateFullName><xnl:PersonName><xnl:NameLine NameType="Initials">C.F.G.R.</xnl:NameLine><xnl:FirstName>Klaar</xnl:FirstName><xnl:NamePrefix></xnl:NamePrefix><xnl:LastName>Koenraad</xnl:LastName></xnl:PersonName></CandidateFullName><Gender>female</Gender><QualifyingAddress><xal:Locality><xal:LocalityName>Roosendaal</xal:LocalityName></xal:Locality></QualifyingAddress></Candidate><Ranking>1</Ranking><Elected>yes</Elected></Selection><Selection><Candidate><CandidateIdentifier Id="2"></CandidateIdentifier><CandidateFullName><xnl:PersonName><xnl:NameLine NameType="Initials">N.</xnl:NameLine><xnl:FirstName>Naima</xnl:FirstName><xnl:NamePrefix></xnl:NamePrefix><xnl:LastName>El Azzouzi</xnl:LastName></xnl:PersonName></CandidateFullName><Gender>female</Gender><QualifyingAddress><xal:Locality><xal:LocalityName>Roosendaal</xal:LocalityName></xal:Locality></QualifyingAddress></Candidate><Ranking>1</Ranking><Elected>yes</Elected></Selection><Selection><Candidate><CandidateIdentifier Id="3"></CandidateIdentifier><CandidateFullName><xnl:PersonName><xnl:NameLine NameType="Initials">C.</xnl:NameLine><xnl:FirstName>Chahira</xnl:FirstName><xnl:NamePrefix></xnl:NamePrefix><xnl:LastName>Mediani</xnl:LastName></xnl:PersonName></CandidateFullName><Gender>female</Gender><QualifyingAddress><xal:Locality><xal:LocalityName>Roosendaal</xal:LocalityName></xal:Locality></QualifyingAddress></Candidate><Ranking>2</Ranking><Elected>yes</Elected></Selection><Selection><AffiliationIdentifier Id="6"><RegisteredName>Partij van de Arbeid (P.v.d.A.)</RegisteredName></AffiliationIdentifier><Elected>yes</Elected></Selection><Selection><Candidate><CandidateIdentifier Id="1"></CandidateIdentifier><CandidateFullName><xnl:PersonName><xnl:NameLine NameType="Initials">B.</xnl:NameLine><xnl:FirstName>Björn</xnl:FirstName><xnl:NamePrefix></xnl:NamePrefix><xnl:LastName>Rommens</xnl:LastName></xnl:PersonName></CandidateFullName><Gender>male</Gender><QualifyingAddress><xal:Locality><xal:LocalityName>Roosendaal</xal:LocalityName></xal:Locality></QualifyingAddress></Candidate><Ranking>1</Ranking><Elected>yes</Elected></Selection><Selection><Candidate><CandidateIdentifier Id="2"></CandidateIdentifier><CandidateFullName><xnl:PersonName><xnl:NameLine NameType="Initials">P.R.</xnl:NameLine><xnl:FirstName>Paul</xnl:FirstName><xnl:NamePrefix></xnl:NamePrefix><xnl:LastName>Klaver</xnl:LastName></xnl:PersonName></CandidateFullName><Gender>male</Gender><QualifyingAddress><xal:Locality><xal:LocalityName>Roosendaal</xal:LocalityName></xal:Locality></QualifyingAddress></Candidate><Ranking>1</Ranking><Elected>yes</Elected></Selection><Selection><AffiliationIdentifier Id="7"><RegisteredName>D66</RegisteredName></AffiliationIdentifier><Elected>yes</Elected></Selection><Selection><Candidate><CandidateIdentifier Id="1"></CandidateIdentifier><CandidateFullName><xnl:PersonName><xnl:NameLine NameType="Initials">B.</xnl:NameLine><xnl:FirstName>Bejar</xnl:FirstName><xnl:NamePrefix></xnl:NamePrefix><xnl:LastName>Taher</xnl:LastName></xnl:PersonName></CandidateFullName><Gender>male</Gender><QualifyingAddress><xal:Locality><xal:LocalityName>Roosendaal</xal:LocalityName></xal:Locality></QualifyingAddress></Candidate><Ranking>1</Ranking><Elected>yes</Elected></Selection><Selection><Candidate><CandidateIdentifier Id="2"></CandidateIdentifier><CandidateFullName><xnl:PersonName><xnl:NameLine NameType="Initials">F.</xnl:NameLine><xnl:FirstName>Femke</xnl:FirstName><xnl:NamePrefix></xnl:NamePrefix><xnl:LastName>Peters</xnl:LastName></xnl:PersonName></CandidateFullName><Gender>female</Gender><QualifyingAddress><xal:Locality><xal:LocalityName>Roosendaal</xal:LocalityName></xal:Locality></QualifyingAddress></Candidate><Ranking>1</Ranking><Elected>yes</Elected></Selection><Selection><AffiliationIdentifier Id="9"><RegisteredName>Forum voor Democratie</RegisteredName></AffiliationIdentifier><Elected>yes</Elected></Selection><Selection><Candidate><CandidateIdentifier Id="1"></CandidateIdentifier><CandidateFullName><xnl:PersonName><xnl:NameLine NameType="Initials">C.S.A.</xnl:NameLine><xnl:FirstName></xnl:FirstName><xnl:NamePrefix>van</xnl:NamePrefix><xnl:LastName>Leerzem</xnl:LastName></xnl:PersonName></CandidateFullName><QualifyingAddress><xal:Locality><xal:LocalityName>Roosendaal</xal:LocalityName></xal:Locality></QualifyingAddress></Candidate><Ranking>1</Ranking><Elected>yes</Elected></Selection><Selection><AffiliationIdentifier Id="10"><RegisteredName>Vitaal Liberaal</RegisteredName></AffiliationIdentifier><Elected>yes</Elected></Selection><Selection><Candidate><CandidateIdentifier Id="1"></CandidateIdentifier><CandidateFullName><xnl:PersonName><xnl:NameLine NameType="Initials">J.J.M.M.</xnl:NameLine><xnl:FirstName>Jac</xnl:FirstName><xnl:NamePrefix></xnl:NamePrefix><xnl:LastName>Wezenbeek</xnl:LastName></xnl:PersonName></CandidateFullName><Gender>male</Gender><QualifyingAddress><xal:Locality><xal:LocalityName>Roosendaal</xal:LocalityName></xal:Locality></QualifyingAddress></Candidate><Ranking>1</Ranking><Elected>yes</Elected></Selection><Selection><AffiliationIdentifier Id="11"><RegisteredName>Burgerbelangen Roosendaal</RegisteredName></AffiliationIdentifier><Elected>yes</Elected></Selection><Selection><Candidate><CandidateIdentifier Id="1"></CandidateIdentifier><CandidateFullName><xnl:PersonName><xnl:NameLine NameType="Initials">S.</xnl:NameLine><xnl:FirstName>Selda</xnl:FirstName><xnl:NamePrefix></xnl:NamePrefix><xnl:LastName>Bozkurt</xnl:LastName></xnl:PersonName></CandidateFullName><Gender>female</Gender><QualifyingAddress><xal:Locality><xal:LocalityName>Roosendaal</xal:LocalityName></xal:Locality></QualifyingAddress></Candidate><Ranking>1</Ranking><Elected>yes</Elected></Selection></Contest></Election></Result></EML>