<EML xmlns="urn:oasis:names:tc:evs:schema:eml" xmlns:ds="http://www.w3.org/2000/09/xmldsig#" xmlns:kr="http://www.kiesraad.nl/extensions" xmlns:xal="urn:oasis:names:tc:ciq:xsdschema:xAL:2.0" xmlns:xnl="urn:oasis:names:tc:ciq:xsdschema:xNL:2.0" Id="520" SchemaVersion="5"><TransactionId>1</TransactionId><ManagingAuthority><AuthorityIdentifier Id="CSB">Waalwijk</AuthorityIdentifier><AuthorityAddress></AuthorityAddress></ManagingAuthority><kr:CreationDateTime>2022-03-17T01:06:54.357</kr:CreationDateTime><ds:CanonicalizationMethod Algorithm="http://www.w3.org/TR/2001/REC-xml-c14n-20010315#WithComments"></ds:CanonicalizationMethod><Result><Election><ElectionIdentifier Id="GR2022_Waalwijk"><ElectionName>Gemeenteraad Waalwijk 2022</ElectionName><ElectionCategory>GR</ElectionCategory><kr:ElectionSubcategory>GR2</kr:ElectionSubcategory><kr:ElectionDomain Id="0867">Waalwijk</kr:ElectionDomain><kr:ElectionDate>2022-03-16</kr:ElectionDate></ElectionIdentifier><Contest><ContestIdentifier Id="geen"></ContestIdentifier><Selection><AffiliationIdentifier Id="1"><RegisteredName>Lokaal Belang</RegisteredName></AffiliationIdentifier><Elected>yes</Elected></Selection><Selection><Candidate><CandidateIdentifier Id="1"></CandidateIdentifier><CandidateFullName><xnl:PersonName><xnl:NameLine NameType="Initials">T.A.B.</xnl:NameLine><xnl:FirstName>Timon</xnl:FirstName><xnl:NamePrefix></xnl:NamePrefix><xnl:LastName>Klerx</xnl:LastName></xnl:PersonName></CandidateFullName><Gender>male</Gender><QualifyingAddress><xal:Locality><xal:LocalityName>Waalwijk</xal:LocalityName></xal:Locality></QualifyingAddress></Candidate><Ranking>1</Ranking><Elected>yes</Elected></Selection><Selection><Candidate><CandidateIdentifier Id="2"></CandidateIdentifier><CandidateFullName><xnl:PersonName><xnl:NameLine NameType="Initials">M.P.A.</xnl:NameLine><xnl:FirstName>Maud</xnl:FirstName><xnl:NamePrefix></xnl:NamePrefix><xnl:LastName>Veraa</xnl:LastName></xnl:PersonName></CandidateFullName><Gender>female</Gender><QualifyingAddress><xal:Locality><xal:LocalityName>Waalwijk</xal:LocalityName></xal:Locality></QualifyingAddress></Candidate><Ranking>1</Ranking><Elected>yes</Elected></Selection><Selection><Candidate><CandidateIdentifier Id="3"></CandidateIdentifier><CandidateFullName><xnl:PersonName><xnl:NameLine NameType="Initials">S.J.A.</xnl:NameLine><xnl:FirstName>Stefan</xnl:FirstName><xnl:NamePrefix></xnl:NamePrefix><xnl:LastName>Montens</xnl:LastName></xnl:PersonName></CandidateFullName><Gender>male</Gender><QualifyingAddress><xal:Locality><xal:LocalityName>Waspik</xal:LocalityName></xal:Locality></QualifyingAddress></Candidate><Ranking>1</Ranking><Elected>yes</Elected></Selection><Selection><Candidate><CandidateIdentifier Id="4"></CandidateIdentifier><CandidateFullName><xnl:PersonName><xnl:NameLine NameType="Initials">M.J.C.</xnl:NameLine><xnl:FirstName>John</xnl:FirstName><xnl:NamePrefix>van den</xnl:NamePrefix><xnl:LastName>Hoven</xnl:LastName></xnl:PersonName></CandidateFullName><Gender>male</Gender><QualifyingAddress><xal:Locality><xal:LocalityName>Waalwijk</xal:LocalityName></xal:Locality></QualifyingAddress></Candidate><Ranking>1</Ranking><Elected>yes</Elected></Selection><Selection><Candidate><CandidateIdentifier Id="5"></CandidateIdentifier><CandidateFullName><xnl:PersonName><xnl:NameLine NameType="Initials">B.</xnl:NameLine><xnl:FirstName>Benan</xnl:FirstName><xnl:NamePrefix></xnl:NamePrefix><xnl:LastName>Koptagel - Demirbas</xnl:LastName></xnl:PersonName></CandidateFullName><Gender>female</Gender><QualifyingAddress><xal:Locality><xal:LocalityName>Waalwijk</xal:LocalityName></xal:Locality></QualifyingAddress></Candidate><Ranking>1</Ranking><Elected>yes</Elected></Selection><Selection><Candidate><CandidateIdentifier Id="6"></CandidateIdentifier><CandidateFullName><xnl:PersonName><xnl:NameLine NameType="Initials">J.M.</xnl:NameLine><xnl:FirstName>Jan</xnl:FirstName><xnl:NamePrefix>van</xnl:NamePrefix><xnl:LastName>Baardwijk</xnl:LastName></xnl:PersonName></CandidateFullName><Gender>male</Gender><QualifyingAddress><xal:Locality><xal:LocalityName>Sprang-Capelle</xal:LocalityName></xal:Locality></QualifyingAddress></Candidate><Ranking>1</Ranking><Elected>yes</Elected></Selection><Selection><Candidate><CandidateIdentifier Id="7"></CandidateIdentifier><CandidateFullName><xnl:PersonName><xnl:NameLine NameType="Initials">S.P.</xnl:NameLine><xnl:FirstName>Bas</xnl:FirstName><xnl:NamePrefix></xnl:NamePrefix><xnl:LastName>Bruurmijn</xnl:LastName></xnl:PersonName></CandidateFullName><Gender>male</Gender><QualifyingAddress><xal:Locality><xal:LocalityName>Waalwijk</xal:LocalityName></xal:Locality></QualifyingAddress></Candidate><Ranking>1</Ranking><Elected>yes</Elected></Selection><Selection><Candidate><CandidateIdentifier Id="8"></CandidateIdentifier><CandidateFullName><xnl:PersonName><xnl:NameLine NameType="Initials">N.E.W.</xnl:NameLine><xnl:FirstName>Niels</xnl:FirstName><xnl:NamePrefix>van der</xnl:NamePrefix><xnl:LastName>Pluijm</xnl:LastName></xnl:PersonName></CandidateFullName><Gender>male</Gender><QualifyingAddress><xal:Locality><xal:LocalityName>Waalwijk</xal:LocalityName></xal:Locality></QualifyingAddress></Candidate><Ranking>1</Ranking><Elected>yes</Elected></Selection><Selection><Candidate><CandidateIdentifier Id="9"></CandidateIdentifier><CandidateFullName><xnl:PersonName><xnl:NameLine NameType="Initials">J.T.M.</xnl:NameLine><xnl:FirstName>Jan</xnl:FirstName><xnl:NamePrefix>van</xnl:NamePrefix><xnl:LastName>Dijk</xnl:LastName></xnl:PersonName></CandidateFullName><Gender>male</Gender><QualifyingAddress><xal:Locality><xal:LocalityName>Waalwijk</xal:LocalityName></xal:Locality></QualifyingAddress></Candidate><Ranking>1</Ranking><Elected>yes</Elected></Selection><Selection><Candidate><CandidateIdentifier Id="10"></CandidateIdentifier><CandidateFullName><xnl:PersonName><xnl:NameLine NameType="Initials">A.A.</xnl:NameLine><xnl:FirstName>Ad</xnl:FirstName><xnl:NamePrefix>van</xnl:NamePrefix><xnl:LastName>Hamond</xnl:LastName></xnl:PersonName></CandidateFullName><Gender>male</Gender><QualifyingAddress><xal:Locality><xal:LocalityName>Waalwijk</xal:LocalityName></xal:Locality></QualifyingAddress></Candidate><Ranking>1</Ranking><Elected>yes</Elected></Selection><Selection><Candidate><CandidateIdentifier Id="11"></CandidateIdentifier><CandidateFullName><xnl:PersonName><xnl:NameLine NameType="Initials">M.J.M.</xnl:NameLine><xnl:FirstName>Marja</xnl:FirstName><xnl:NamePrefix></xnl:NamePrefix><xnl:LastName>Verhagen - van Lier</xnl:LastName></xnl:PersonName></CandidateFullName><Gender>female</Gender><QualifyingAddress><xal:Locality><xal:LocalityName>Waalwijk</xal:LocalityName></xal:Locality></QualifyingAddress></Candidate><Ranking>1</Ranking><Elected>yes</Elected></Selection><Selection><AffiliationIdentifier Id="2"><RegisteredName>VVD</RegisteredName></AffiliationIdentifier><Elected>yes</Elected></Selection><Selection><Candidate><CandidateIdentifier Id="1"></CandidateIdentifier><CandidateFullName><xnl:PersonName><xnl:NameLine NameType="Initials">I.C.</xnl:NameLine><xnl:FirstName>Ilona</xnl:FirstName><xnl:NamePrefix></xnl:NamePrefix><xnl:LastName>Klerks</xnl:LastName></xnl:PersonName></CandidateFullName><Gender>female</Gender><QualifyingAddress><xal:Locality><xal:LocalityName>Waalwijk</xal:LocalityName></xal:Locality></QualifyingAddress></Candidate><Ranking>1</Ranking><Elected>yes</Elected></Selection><Selection><Candidate><CandidateIdentifier Id="2"></CandidateIdentifier><CandidateFullName><xnl:PersonName><xnl:NameLine NameType="Initials">T.F.J.H.</xnl:NameLine><xnl:FirstName>Frank</xnl:FirstName><xnl:NamePrefix></xnl:NamePrefix><xnl:LastName>Spierings</xnl:LastName></xnl:PersonName></CandidateFullName><Gender>male</Gender><QualifyingAddress><xal:Locality><xal:LocalityName>Waalwijk</xal:LocalityName></xal:Locality></QualifyingAddress></Candidate><Ranking>1</Ranking><Elected>yes</Elected></Selection><Selection><Candidate><CandidateIdentifier Id="3"></CandidateIdentifier><CandidateFullName><xnl:PersonName><xnl:NameLine NameType="Initials">R.</xnl:NameLine><xnl:FirstName>Ronald</xnl:FirstName><xnl:NamePrefix></xnl:NamePrefix><xnl:LastName>Bakker</xnl:LastName></xnl:PersonName></CandidateFullName><Gender>male</Gender><QualifyingAddress><xal:Locality><xal:LocalityName>Sprang-Capelle</xal:LocalityName></xal:Locality></QualifyingAddress></Candidate><Ranking>1</Ranking><Elected>yes</Elected></Selection><Selection><Candidate><CandidateIdentifier Id="4"></CandidateIdentifier><CandidateFullName><xnl:PersonName><xnl:NameLine NameType="Initials">M.</xnl:NameLine><xnl:FirstName>Miloš</xnl:FirstName><xnl:NamePrefix></xnl:NamePrefix><xnl:LastName>Bokšan</xnl:LastName></xnl:PersonName></CandidateFullName><Gender>male</Gender><QualifyingAddress><xal:Locality><xal:LocalityName>Waalwijk</xal:LocalityName></xal:Locality></QualifyingAddress></Candidate><Ranking>2</Ranking><Elected>yes</Elected></Selection><Selection><AffiliationIdentifier Id="3"><RegisteredName>GroenLinksaf</RegisteredName></AffiliationIdentifier><Elected>yes</Elected></Selection><Selection><Candidate><CandidateIdentifier Id="1"></CandidateIdentifier><CandidateFullName><xnl:PersonName><xnl:NameLine NameType="Initials">R.</xnl:NameLine><xnl:FirstName>Dilek</xnl:FirstName><xnl:NamePrefix></xnl:NamePrefix><xnl:LastName>Odabasi-Seker</xnl:LastName></xnl:PersonName></CandidateFullName><Gender>female</Gender><QualifyingAddress><xal:Locality><xal:LocalityName>Waalwijk</xal:LocalityName></xal:Locality></QualifyingAddress></Candidate><Ranking>1</Ranking><Elected>yes</Elected></Selection><Selection><Candidate><CandidateIdentifier Id="2"></CandidateIdentifier><CandidateFullName><xnl:PersonName><xnl:NameLine NameType="Initials">F.A.T.</xnl:NameLine><xnl:FirstName>Frank</xnl:FirstName><xnl:NamePrefix>den</xnl:NamePrefix><xnl:LastName>Braven</xnl:LastName></xnl:PersonName></CandidateFullName><Gender>male</Gender><QualifyingAddress><xal:Locality><xal:LocalityName>Waalwijk</xal:LocalityName></xal:Locality></QualifyingAddress></Candidate><Ranking>1</Ranking><Elected>yes</Elected></Selection><Selection><Candidate><CandidateIdentifier Id="3"></CandidateIdentifier><CandidateFullName><xnl:PersonName><xnl:NameLine NameType="Initials">M.Y.</xnl:NameLine><xnl:FirstName>Yvette</xnl:FirstName><xnl:NamePrefix>van</xnl:NamePrefix><xnl:LastName>Laar</xnl:LastName></xnl:PersonName></CandidateFullName><Gender>female</Gender><QualifyingAddress><xal:Locality><xal:LocalityName>Sprang-Capelle</xal:LocalityName></xal:Locality></QualifyingAddress></Candidate><Ranking>1</Ranking><Elected>yes</Elected></Selection><Selection><AffiliationIdentifier Id="4"><RegisteredName>CDA</RegisteredName></AffiliationIdentifier><Elected>yes</Elected></Selection><Selection><Candidate><CandidateIdentifier Id="1"></CandidateIdentifier><CandidateFullName><xnl:PersonName><xnl:NameLine NameType="Initials">R.J.M.</xnl:NameLine><xnl:FirstName>Ruud</xnl:FirstName><xnl:NamePrefix></xnl:NamePrefix><xnl:LastName>Spohr</xnl:LastName></xnl:PersonName></CandidateFullName><Gender>male</Gender><QualifyingAddress><xal:Locality><xal:LocalityName>Sprang-Capelle</xal:LocalityName></xal:Locality></QualifyingAddress></Candidate><Ranking>1</Ranking><Elected>yes</Elected></Selection><Selection><Candidate><CandidateIdentifier Id="2"></CandidateIdentifier><CandidateFullName><xnl:PersonName><xnl:NameLine NameType="Initials">F.I.H.M.</xnl:NameLine><xnl:FirstName>Cissy</xnl:FirstName><xnl:NamePrefix>de</xnl:NamePrefix><xnl:LastName>Bruijn</xnl:LastName></xnl:PersonName></CandidateFullName><Gender>female</Gender><QualifyingAddress><xal:Locality><xal:LocalityName>Waspik</xal:LocalityName></xal:Locality></QualifyingAddress></Candidate><Ranking>1</Ranking><Elected>yes</Elected></Selection><Selection><AffiliationIdentifier Id="5"><RegisteredName>D66</RegisteredName></AffiliationIdentifier><Elected>yes</Elected></Selection><Selection><Candidate><CandidateIdentifier Id="1"></CandidateIdentifier><CandidateFullName><xnl:PersonName><xnl:NameLine NameType="Initials">C.G.W.M.C</xnl:NameLine><xnl:FirstName>Sheila</xnl:FirstName><xnl:NamePrefix></xnl:NamePrefix><xnl:LastName>Schuijffel</xnl:LastName></xnl:PersonName></CandidateFullName><QualifyingAddress><xal:Locality><xal:LocalityName>Waalwijk</xal:LocalityName></xal:Locality></QualifyingAddress></Candidate><Ranking>1</Ranking><Elected>yes</Elected></Selection><Selection><Candidate><CandidateIdentifier Id="2"></CandidateIdentifier><CandidateFullName><xnl:PersonName><xnl:NameLine NameType="Initials">T.</xnl:NameLine><xnl:FirstName>Tommie</xnl:FirstName><xnl:NamePrefix></xnl:NamePrefix><xnl:LastName>Mertens</xnl:LastName></xnl:PersonName></CandidateFullName><QualifyingAddress><xal:Locality><xal:LocalityName>Waalwijk</xal:LocalityName></xal:Locality></QualifyingAddress></Candidate><Ranking>2</Ranking><Elected>yes</Elected></Selection><Selection><AffiliationIdentifier Id="6"><RegisteredName>Staatkundig Gereformeerde Partij (SGP)</RegisteredName></AffiliationIdentifier><Elected>yes</Elected></Selection><Selection><Candidate><CandidateIdentifier Id="1"></CandidateIdentifier><CandidateFullName><xnl:PersonName><xnl:NameLine NameType="Initials">R.A.A.</xnl:NameLine><xnl:FirstName>Richard</xnl:FirstName><xnl:NamePrefix></xnl:NamePrefix><xnl:LastName>Tiemstra</xnl:LastName></xnl:PersonName></CandidateFullName><QualifyingAddress><xal:Locality><xal:LocalityName>Sprang-Capelle</xal:LocalityName></xal:Locality></QualifyingAddress></Candidate><Ranking>1</Ranking><Elected>yes</Elected></Selection><Selection><Candidate><CandidateIdentifier Id="2"></CandidateIdentifier><CandidateFullName><xnl:PersonName><xnl:NameLine NameType="Initials">H.J.</xnl:NameLine><xnl:FirstName>Henk</xnl:FirstName><xnl:NamePrefix>van</xnl:NamePrefix><xnl:LastName>Zelst</xnl:LastName></xnl:PersonName></CandidateFullName><QualifyingAddress><xal:Locality><xal:LocalityName>Sprang-Capelle</xal:LocalityName></xal:Locality></QualifyingAddress></Candidate><Ranking>1</Ranking><Elected>yes</Elected></Selection><Selection><AffiliationIdentifier Id="7"><RegisteredName>Lijst IJpelaar</RegisteredName></AffiliationIdentifier><Elected>yes</Elected></Selection><Selection><Candidate><CandidateIdentifier Id="1"></CandidateIdentifier><CandidateFullName><xnl:PersonName><xnl:NameLine NameType="Initials">E.Y.</xnl:NameLine><xnl:FirstName>Yvette</xnl:FirstName><xnl:NamePrefix></xnl:NamePrefix><xnl:LastName>IJpelaar - Alias</xnl:LastName></xnl:PersonName></CandidateFullName><Gender>female</Gender><QualifyingAddress><xal:Locality><xal:LocalityName>Waalwijk</xal:LocalityName></xal:Locality></QualifyingAddress></Candidate><Ranking>1</Ranking><Elected>yes</Elected></Selection><Selection><AffiliationIdentifier Id="8"><RegisteredName>ChristenUnie</RegisteredName></AffiliationIdentifier><Elected>yes</Elected></Selection><Selection><Candidate><CandidateIdentifier Id="1"></CandidateIdentifier><CandidateFullName><xnl:PersonName><xnl:NameLine NameType="Initials">J.</xnl:NameLine><xnl:FirstName>Jan</xnl:FirstName><xnl:NamePrefix>van</xnl:NamePrefix><xnl:LastName>Groos</xnl:LastName></xnl:PersonName></CandidateFullName><Gender>male</Gender><QualifyingAddress><xal:Locality><xal:LocalityName>Waalwijk</xal:LocalityName></xal:Locality></QualifyingAddress></Candidate><Ranking>1</Ranking><Elected>yes</Elected></Selection><Selection><AffiliationIdentifier Id="9"><RegisteredName></RegisteredName></AffiliationIdentifier><Elected>yes</Elected></Selection><Selection><Candidate><CandidateIdentifier Id="1"></CandidateIdentifier><CandidateFullName><xnl:PersonName><xnl:NameLine NameType="Initials">N.R.W.A.</xnl:NameLine><xnl:FirstName>Niels</xnl:FirstName><xnl:NamePrefix></xnl:NamePrefix><xnl:LastName>Aussems</xnl:LastName></xnl:PersonName></CandidateFullName><Gender>male</Gender><QualifyingAddress><xal:Locality><xal:LocalityName>Sprang-Capelle</xal:LocalityName></xal:Locality></QualifyingAddress></Candidate><Ranking>1</Ranking><Elected>yes</Elected></Selection><Selection><AffiliationIdentifier Id="10"><RegisteredName>Samen Waalwijk</RegisteredName></AffiliationIdentifier><Elected>yes</Elected></Selection><Selection><Candidate><CandidateIdentifier Id="1"></CandidateIdentifier><CandidateFullName><xnl:PersonName><xnl:NameLine NameType="Initials">E.A</xnl:NameLine><xnl:FirstName>Bea</xnl:FirstName><xnl:NamePrefix>de</xnl:NamePrefix><xnl:LastName>Jongste - van Heijst</xnl:LastName></xnl:PersonName></CandidateFullName><Gender>female</Gender><QualifyingAddress><xal:Locality><xal:LocalityName>Waalwijk</xal:LocalityName></xal:Locality></QualifyingAddress></Candidate><Ranking>1</Ranking><Elected>yes</Elected></Selection><Selection><Candidate><CandidateIdentifier Id="2"></CandidateIdentifier><CandidateFullName><xnl:PersonName><xnl:NameLine NameType="Initials">L</xnl:NameLine><xnl:FirstName>Luuk</xnl:FirstName><xnl:NamePrefix></xnl:NamePrefix><xnl:LastName>Ottens</xnl:LastName></xnl:PersonName></CandidateFullName><Gender>male</Gender><QualifyingAddress><xal:Locality><xal:LocalityName>Waalwijk</xal:LocalityName></xal:Locality></QualifyingAddress></Candidate><Ranking>2</Ranking><Elected>yes</Elected></Selection></Contest></Election></Result></EML>