<EML xmlns="urn:oasis:names:tc:evs:schema:eml" xmlns:ds="http://www.w3.org/2000/09/xmldsig#" xmlns:kr="http://www.kiesraad.nl/extensions" xmlns:xal="urn:oasis:names:tc:ciq:xsdschema:xAL:2.0" xmlns:xnl="urn:oasis:names:tc:ciq:xsdschema:xNL:2.0" Id="520" SchemaVersion="5"><TransactionId>1</TransactionId><ManagingAuthority><AuthorityIdentifier Id="CSB">Zeewolde</AuthorityIdentifier><AuthorityAddress></AuthorityAddress></ManagingAuthority><kr:CreationDateTime>2022-03-17T01:01:42.200</kr:CreationDateTime><ds:CanonicalizationMethod Algorithm="http://www.w3.org/TR/2001/REC-xml-c14n-20010315#WithComments"></ds:CanonicalizationMethod><Result><Election><ElectionIdentifier Id="GR2022_Zeewolde"><ElectionName>Gemeenteraad Zeewolde 2022</ElectionName><ElectionCategory>GR</ElectionCategory><kr:ElectionSubcategory>GR2</kr:ElectionSubcategory><kr:ElectionDomain Id="0050">Zeewolde</kr:ElectionDomain><kr:ElectionDate>2022-03-16</kr:ElectionDate></ElectionIdentifier><Contest><ContestIdentifier Id="geen"></ContestIdentifier><Selection><AffiliationIdentifier Id="1"><RegisteredName>Leefbaar Zeewolde</RegisteredName></AffiliationIdentifier><Elected>yes</Elected></Selection><Selection><Candidate><CandidateIdentifier Id="1"></CandidateIdentifier><CandidateFullName><xnl:PersonName><xnl:NameLine NameType="Initials">T.C.M.</xnl:NameLine><xnl:FirstName>Tom</xnl:FirstName><xnl:NamePrefix></xnl:NamePrefix><xnl:LastName>Zonneveld</xnl:LastName></xnl:PersonName></CandidateFullName><Gender>male</Gender><QualifyingAddress><xal:Locality><xal:LocalityName>Zeewolde</xal:LocalityName></xal:Locality></QualifyingAddress></Candidate><Ranking>1</Ranking><Elected>yes</Elected></Selection><Selection><Candidate><CandidateIdentifier Id="2"></CandidateIdentifier><CandidateFullName><xnl:PersonName><xnl:NameLine NameType="Initials">W.C.</xnl:NameLine><xnl:FirstName>Winnie</xnl:FirstName><xnl:NamePrefix></xnl:NamePrefix><xnl:LastName>Prins</xnl:LastName></xnl:PersonName></CandidateFullName><Gender>female</Gender><QualifyingAddress><xal:Locality><xal:LocalityName>Zeewolde</xal:LocalityName></xal:Locality></QualifyingAddress></Candidate><Ranking>1</Ranking><Elected>yes</Elected></Selection><Selection><Candidate><CandidateIdentifier Id="3"></CandidateIdentifier><CandidateFullName><xnl:PersonName><xnl:NameLine NameType="Initials">E.</xnl:NameLine><xnl:FirstName>Els</xnl:FirstName><xnl:NamePrefix>van</xnl:NamePrefix><xnl:LastName>Es</xnl:LastName></xnl:PersonName></CandidateFullName><Gender>female</Gender><QualifyingAddress><xal:Locality><xal:LocalityName>Zeewolde</xal:LocalityName></xal:Locality></QualifyingAddress></Candidate><Ranking>1</Ranking><Elected>yes</Elected></Selection><Selection><Candidate><CandidateIdentifier Id="4"></CandidateIdentifier><CandidateFullName><xnl:PersonName><xnl:NameLine NameType="Initials">S.J.</xnl:NameLine><xnl:FirstName>Samantha</xnl:FirstName><xnl:NamePrefix>de</xnl:NamePrefix><xnl:LastName>Vries</xnl:LastName></xnl:PersonName></CandidateFullName><Gender>female</Gender><QualifyingAddress><xal:Locality><xal:LocalityName>Zeewolde</xal:LocalityName></xal:Locality></QualifyingAddress></Candidate><Ranking>1</Ranking><Elected>yes</Elected></Selection><Selection><Candidate><CandidateIdentifier Id="5"></CandidateIdentifier><CandidateFullName><xnl:PersonName><xnl:NameLine NameType="Initials">H.L.</xnl:NameLine><xnl:FirstName>Helmut</xnl:FirstName><xnl:NamePrefix></xnl:NamePrefix><xnl:LastName>Hermans</xnl:LastName></xnl:PersonName></CandidateFullName><Gender>male</Gender><QualifyingAddress><xal:Locality><xal:LocalityName>Zeewolde</xal:LocalityName></xal:Locality></QualifyingAddress></Candidate><Ranking>1</Ranking><Elected>yes</Elected></Selection><Selection><Candidate><CandidateIdentifier Id="6"></CandidateIdentifier><CandidateFullName><xnl:PersonName><xnl:NameLine NameType="Initials">E.E.</xnl:NameLine><xnl:FirstName>Betty</xnl:FirstName><xnl:NamePrefix>van den</xnl:NamePrefix><xnl:LastName>Braber-van Ziel</xnl:LastName></xnl:PersonName></CandidateFullName><Gender>female</Gender><QualifyingAddress><xal:Locality><xal:LocalityName>Zeewolde</xal:LocalityName></xal:Locality></QualifyingAddress></Candidate><Ranking>1</Ranking><Elected>yes</Elected></Selection><Selection><Candidate><CandidateIdentifier Id="7"></CandidateIdentifier><CandidateFullName><xnl:PersonName><xnl:NameLine NameType="Initials">B.G.J.S.</xnl:NameLine><xnl:FirstName>Ben</xnl:FirstName><xnl:NamePrefix></xnl:NamePrefix><xnl:LastName>Sonneveld</xnl:LastName></xnl:PersonName></CandidateFullName><Gender>male</Gender><QualifyingAddress><xal:Locality><xal:LocalityName>Zeewolde</xal:LocalityName></xal:Locality></QualifyingAddress></Candidate><Ranking>1</Ranking><Elected>yes</Elected></Selection><Selection><Candidate><CandidateIdentifier Id="8"></CandidateIdentifier><CandidateFullName><xnl:PersonName><xnl:NameLine NameType="Initials">M.H.</xnl:NameLine><xnl:FirstName>Manno</xnl:FirstName><xnl:NamePrefix></xnl:NamePrefix><xnl:LastName>Jonker</xnl:LastName></xnl:PersonName></CandidateFullName><Gender>male</Gender><QualifyingAddress><xal:Locality><xal:LocalityName>Zeewolde</xal:LocalityName></xal:Locality></QualifyingAddress></Candidate><Ranking>2</Ranking><Elected>yes</Elected></Selection><Selection><Candidate><CandidateIdentifier Id="9"></CandidateIdentifier><CandidateFullName><xnl:PersonName><xnl:NameLine NameType="Initials">E.S.</xnl:NameLine><xnl:FirstName>Evert</xnl:FirstName><xnl:NamePrefix></xnl:NamePrefix><xnl:LastName>Ekker</xnl:LastName></xnl:PersonName></CandidateFullName><Gender>male</Gender><QualifyingAddress><xal:Locality><xal:LocalityName>Zeewolde</xal:LocalityName></xal:Locality></QualifyingAddress></Candidate><Ranking>2</Ranking><Elected>yes</Elected></Selection><Selection><Candidate><CandidateIdentifier Id="10"></CandidateIdentifier><CandidateFullName><xnl:PersonName><xnl:NameLine NameType="Initials">T.S.</xnl:NameLine><xnl:FirstName>Theun</xnl:FirstName><xnl:NamePrefix></xnl:NamePrefix><xnl:LastName>Schaaf</xnl:LastName></xnl:PersonName></CandidateFullName><Gender>male</Gender><QualifyingAddress><xal:Locality><xal:LocalityName>Zeewolde</xal:LocalityName></xal:Locality></QualifyingAddress></Candidate><Ranking>2</Ranking><Elected>yes</Elected></Selection><Selection><AffiliationIdentifier Id="2"><RegisteredName>VVD</RegisteredName></AffiliationIdentifier><Elected>yes</Elected></Selection><Selection><Candidate><CandidateIdentifier Id="1"></CandidateIdentifier><CandidateFullName><xnl:PersonName><xnl:NameLine NameType="Initials">J.M.A.</xnl:NameLine><xnl:FirstName>Angela</xnl:FirstName><xnl:NamePrefix></xnl:NamePrefix><xnl:LastName>Huckriede</xnl:LastName></xnl:PersonName></CandidateFullName><Gender>female</Gender><QualifyingAddress><xal:Locality><xal:LocalityName>Zeewolde</xal:LocalityName></xal:Locality></QualifyingAddress></Candidate><Ranking>1</Ranking><Elected>yes</Elected></Selection><Selection><Candidate><CandidateIdentifier Id="2"></CandidateIdentifier><CandidateFullName><xnl:PersonName><xnl:NameLine NameType="Initials">M.A.N.M.</xnl:NameLine><xnl:FirstName>Martijn</xnl:FirstName><xnl:NamePrefix></xnl:NamePrefix><xnl:LastName>Wortman</xnl:LastName></xnl:PersonName></CandidateFullName><Gender>male</Gender><QualifyingAddress><xal:Locality><xal:LocalityName>Zeewolde</xal:LocalityName></xal:Locality></QualifyingAddress></Candidate><Ranking>1</Ranking><Elected>yes</Elected></Selection><Selection><AffiliationIdentifier Id="3"><RegisteredName>ChristenUnie</RegisteredName></AffiliationIdentifier><Elected>yes</Elected></Selection><Selection><Candidate><CandidateIdentifier Id="1"></CandidateIdentifier><CandidateFullName><xnl:PersonName><xnl:NameLine NameType="Initials">A.T.</xnl:NameLine><xnl:FirstName>Tamara</xnl:FirstName><xnl:NamePrefix></xnl:NamePrefix><xnl:LastName>Baas</xnl:LastName></xnl:PersonName></CandidateFullName><Gender>female</Gender><QualifyingAddress><xal:Locality><xal:LocalityName>Zeewolde</xal:LocalityName></xal:Locality></QualifyingAddress></Candidate><Ranking>1</Ranking><Elected>yes</Elected></Selection><Selection><Candidate><CandidateIdentifier Id="2"></CandidateIdentifier><CandidateFullName><xnl:PersonName><xnl:NameLine NameType="Initials">E.L.</xnl:NameLine><xnl:FirstName>Erik</xnl:FirstName><xnl:NamePrefix>van de</xnl:NamePrefix><xnl:LastName>Beld</xnl:LastName></xnl:PersonName></CandidateFullName><Gender>male</Gender><QualifyingAddress><xal:Locality><xal:LocalityName>Zeewolde</xal:LocalityName></xal:Locality></QualifyingAddress></Candidate><Ranking>1</Ranking><Elected>yes</Elected></Selection><Selection><Candidate><CandidateIdentifier Id="3"></CandidateIdentifier><CandidateFullName><xnl:PersonName><xnl:NameLine NameType="Initials">F.</xnl:NameLine><xnl:FirstName>Femke</xnl:FirstName><xnl:NamePrefix>van</xnl:NamePrefix><xnl:LastName>Wijk</xnl:LastName></xnl:PersonName></CandidateFullName><Gender>female</Gender><QualifyingAddress><xal:Locality><xal:LocalityName>Zeewolde</xal:LocalityName></xal:Locality></QualifyingAddress></Candidate><Ranking>1</Ranking><Elected>yes</Elected></Selection><Selection><Candidate><CandidateIdentifier Id="4"></CandidateIdentifier><CandidateFullName><xnl:PersonName><xnl:NameLine NameType="Initials">G.S.</xnl:NameLine><xnl:FirstName>Gerard</xnl:FirstName><xnl:NamePrefix>den</xnl:NamePrefix><xnl:LastName>Bakker</xnl:LastName></xnl:PersonName></CandidateFullName><Gender>male</Gender><QualifyingAddress><xal:Locality><xal:LocalityName>Zeewolde</xal:LocalityName></xal:Locality></QualifyingAddress></Candidate><Ranking>2</Ranking><Elected>yes</Elected></Selection><Selection><AffiliationIdentifier Id="4"><RegisteredName>D66</RegisteredName></AffiliationIdentifier><Elected>yes</Elected></Selection><Selection><Candidate><CandidateIdentifier Id="1"></CandidateIdentifier><CandidateFullName><xnl:PersonName><xnl:NameLine NameType="Initials">W.J.</xnl:NameLine><xnl:FirstName>Wenda</xnl:FirstName><xnl:NamePrefix></xnl:NamePrefix><xnl:LastName>Westerhuis</xnl:LastName></xnl:PersonName></CandidateFullName><Gender>female</Gender><QualifyingAddress><xal:Locality><xal:LocalityName>Zeewolde</xal:LocalityName></xal:Locality></QualifyingAddress></Candidate><Ranking>1</Ranking><Elected>yes</Elected></Selection><Selection><AffiliationIdentifier Id="5"><RegisteredName>CDA</RegisteredName></AffiliationIdentifier><Elected>yes</Elected></Selection><Selection><Candidate><CandidateIdentifier Id="1"></CandidateIdentifier><CandidateFullName><xnl:PersonName><xnl:NameLine NameType="Initials">E.J.</xnl:NameLine><xnl:FirstName>Egge Jan</xnl:FirstName><xnl:NamePrefix>de</xnl:NamePrefix><xnl:LastName>Jonge</xnl:LastName></xnl:PersonName></CandidateFullName><Gender>male</Gender><QualifyingAddress><xal:Locality><xal:LocalityName>Zeewolde</xal:LocalityName></xal:Locality></QualifyingAddress></Candidate><Ranking>1</Ranking><Elected>yes</Elected></Selection><Selection><AffiliationIdentifier Id="6"><RegisteredName>Actief Zeewolde</RegisteredName></AffiliationIdentifier><Elected>yes</Elected></Selection><Selection><Candidate><CandidateIdentifier Id="1"></CandidateIdentifier><CandidateFullName><xnl:PersonName><xnl:NameLine NameType="Initials">Y.M.</xnl:NameLine><xnl:FirstName>Yvonne</xnl:FirstName><xnl:NamePrefix>van</xnl:NamePrefix><xnl:LastName>Bruggen</xnl:LastName></xnl:PersonName></CandidateFullName><Gender>female</Gender><QualifyingAddress><xal:Locality><xal:LocalityName>Zeewolde</xal:LocalityName></xal:Locality></QualifyingAddress></Candidate><Ranking>1</Ranking><Elected>yes</Elected></Selection></Contest></Election></Result></EML>