<EML xmlns="urn:oasis:names:tc:evs:schema:eml" xmlns:ds="http://www.w3.org/2000/09/xmldsig#" xmlns:kr="http://www.kiesraad.nl/extensions" xmlns:xal="urn:oasis:names:tc:ciq:xsdschema:xAL:2.0" xmlns:xnl="urn:oasis:names:tc:ciq:xsdschema:xNL:2.0" Id="520" SchemaVersion="5"><TransactionId>1</TransactionId><ManagingAuthority><AuthorityIdentifier Id="CSB">Best</AuthorityIdentifier><AuthorityAddress></AuthorityAddress></ManagingAuthority><kr:CreationDateTime>2022-03-17T00:28:37.456</kr:CreationDateTime><ds:CanonicalizationMethod Algorithm="http://www.w3.org/TR/2001/REC-xml-c14n-20010315#WithComments"></ds:CanonicalizationMethod><Result><Election><ElectionIdentifier Id="GR2022_Best"><ElectionName>Gemeenteraad Best 2022</ElectionName><ElectionCategory>GR</ElectionCategory><kr:ElectionSubcategory>GR2</kr:ElectionSubcategory><kr:ElectionDomain Id="0753">Best</kr:ElectionDomain><kr:ElectionDate>2022-03-16</kr:ElectionDate></ElectionIdentifier><Contest><ContestIdentifier Id="geen"></ContestIdentifier><Selection><AffiliationIdentifier Id="1"><RegisteredName>VVD</RegisteredName></AffiliationIdentifier><Elected>yes</Elected></Selection><Selection><Candidate><CandidateIdentifier Id="1"></CandidateIdentifier><CandidateFullName><xnl:PersonName><xnl:NameLine NameType="Initials">J.H.E.</xnl:NameLine><xnl:FirstName>John</xnl:FirstName><xnl:NamePrefix></xnl:NamePrefix><xnl:LastName>Verheijen</xnl:LastName></xnl:PersonName></CandidateFullName><Gender>male</Gender><QualifyingAddress><xal:Locality><xal:LocalityName>Best</xal:LocalityName></xal:Locality></QualifyingAddress></Candidate><Ranking>1</Ranking><Elected>yes</Elected></Selection><Selection><Candidate><CandidateIdentifier Id="2"></CandidateIdentifier><CandidateFullName><xnl:PersonName><xnl:NameLine NameType="Initials">I.H.J.</xnl:NameLine><xnl:FirstName>Ilona</xnl:FirstName><xnl:NamePrefix></xnl:NamePrefix><xnl:LastName>Vink-Bressers</xnl:LastName></xnl:PersonName></CandidateFullName><Gender>female</Gender><QualifyingAddress><xal:Locality><xal:LocalityName>Best</xal:LocalityName></xal:Locality></QualifyingAddress></Candidate><Ranking>1</Ranking><Elected>yes</Elected></Selection><Selection><Candidate><CandidateIdentifier Id="3"></CandidateIdentifier><CandidateFullName><xnl:PersonName><xnl:NameLine NameType="Initials">L.T.M.</xnl:NameLine><xnl:FirstName>Linda</xnl:FirstName><xnl:NamePrefix>van</xnl:NamePrefix><xnl:LastName>Gerwen-Scheepers</xnl:LastName></xnl:PersonName></CandidateFullName><Gender>female</Gender><QualifyingAddress><xal:Locality><xal:LocalityName>Best</xal:LocalityName></xal:Locality></QualifyingAddress></Candidate><Ranking>1</Ranking><Elected>yes</Elected></Selection><Selection><Candidate><CandidateIdentifier Id="4"></CandidateIdentifier><CandidateFullName><xnl:PersonName><xnl:NameLine NameType="Initials">N.H.C.</xnl:NameLine><xnl:FirstName>Niels</xnl:FirstName><xnl:NamePrefix></xnl:NamePrefix><xnl:LastName>Govers</xnl:LastName></xnl:PersonName></CandidateFullName><Gender>male</Gender><QualifyingAddress><xal:Locality><xal:LocalityName>Best</xal:LocalityName></xal:Locality></QualifyingAddress></Candidate><Ranking>2</Ranking><Elected>yes</Elected></Selection><Selection><AffiliationIdentifier Id="2"><RegisteredName>CDA</RegisteredName></AffiliationIdentifier><Elected>yes</Elected></Selection><Selection><Candidate><CandidateIdentifier Id="1"></CandidateIdentifier><CandidateFullName><xnl:PersonName><xnl:NameLine NameType="Initials">M.L.A.</xnl:NameLine><xnl:FirstName>Marieke</xnl:FirstName><xnl:NamePrefix></xnl:NamePrefix><xnl:LastName>Gondrie</xnl:LastName></xnl:PersonName></CandidateFullName><Gender>female</Gender><QualifyingAddress><xal:Locality><xal:LocalityName>Best</xal:LocalityName></xal:Locality></QualifyingAddress></Candidate><Ranking>1</Ranking><Elected>yes</Elected></Selection><Selection><Candidate><CandidateIdentifier Id="2"></CandidateIdentifier><CandidateFullName><xnl:PersonName><xnl:NameLine NameType="Initials">H.A.</xnl:NameLine><xnl:FirstName>Henk</xnl:FirstName><xnl:NamePrefix>van</xnl:NamePrefix><xnl:LastName>Kuik</xnl:LastName></xnl:PersonName></CandidateFullName><Gender>male</Gender><QualifyingAddress><xal:Locality><xal:LocalityName>Best</xal:LocalityName></xal:Locality></QualifyingAddress></Candidate><Ranking>1</Ranking><Elected>yes</Elected></Selection><Selection><Candidate><CandidateIdentifier Id="3"></CandidateIdentifier><CandidateFullName><xnl:PersonName><xnl:NameLine NameType="Initials">F.M.</xnl:NameLine><xnl:FirstName>Femke</xnl:FirstName><xnl:NamePrefix>de</xnl:NamePrefix><xnl:LastName>Vries</xnl:LastName></xnl:PersonName></CandidateFullName><Gender>female</Gender><QualifyingAddress><xal:Locality><xal:LocalityName>Best</xal:LocalityName></xal:Locality></QualifyingAddress></Candidate><Ranking>1</Ranking><Elected>yes</Elected></Selection><Selection><AffiliationIdentifier Id="3"><RegisteredName>Best Open</RegisteredName></AffiliationIdentifier><Elected>yes</Elected></Selection><Selection><Candidate><CandidateIdentifier Id="1"></CandidateIdentifier><CandidateFullName><xnl:PersonName><xnl:NameLine NameType="Initials">V.J.H.M.</xnl:NameLine><xnl:FirstName>Véronique</xnl:FirstName><xnl:NamePrefix></xnl:NamePrefix><xnl:LastName>Zeeman</xnl:LastName></xnl:PersonName></CandidateFullName><Gender>female</Gender><QualifyingAddress><xal:Locality><xal:LocalityName>Best</xal:LocalityName></xal:Locality></QualifyingAddress></Candidate><Ranking>1</Ranking><Elected>yes</Elected></Selection><Selection><Candidate><CandidateIdentifier Id="2"></CandidateIdentifier><CandidateFullName><xnl:PersonName><xnl:NameLine NameType="Initials">L.B.A.</xnl:NameLine><xnl:FirstName>Leon</xnl:FirstName><xnl:NamePrefix></xnl:NamePrefix><xnl:LastName>Kennis</xnl:LastName></xnl:PersonName></CandidateFullName><Gender>male</Gender><QualifyingAddress><xal:Locality><xal:LocalityName>Best</xal:LocalityName></xal:Locality></QualifyingAddress></Candidate><Ranking>2</Ranking><Elected>yes</Elected></Selection><Selection><Candidate><CandidateIdentifier Id="3"></CandidateIdentifier><CandidateFullName><xnl:PersonName><xnl:NameLine NameType="Initials">A.</xnl:NameLine><xnl:FirstName>Harry</xnl:FirstName><xnl:NamePrefix></xnl:NamePrefix><xnl:LastName>Crielaars</xnl:LastName></xnl:PersonName></CandidateFullName><Gender>male</Gender><QualifyingAddress><xal:Locality><xal:LocalityName>Best</xal:LocalityName></xal:Locality></QualifyingAddress></Candidate><Ranking>2</Ranking><Elected>yes</Elected></Selection><Selection><AffiliationIdentifier Id="4"><RegisteredName>Jongerenpartij JO</RegisteredName></AffiliationIdentifier><Elected>yes</Elected></Selection><Selection><Candidate><CandidateIdentifier Id="1"></CandidateIdentifier><CandidateFullName><xnl:PersonName><xnl:NameLine NameType="Initials">J.J.W.M.</xnl:NameLine><xnl:FirstName>Jo</xnl:FirstName><xnl:NamePrefix>van den</xnl:NamePrefix><xnl:LastName>Boogaard</xnl:LastName></xnl:PersonName></CandidateFullName><Gender>male</Gender><QualifyingAddress><xal:Locality><xal:LocalityName>Best</xal:LocalityName></xal:Locality></QualifyingAddress></Candidate><Ranking>1</Ranking><Elected>yes</Elected></Selection><Selection><Candidate><CandidateIdentifier Id="2"></CandidateIdentifier><CandidateFullName><xnl:PersonName><xnl:NameLine NameType="Initials">I.M.S.T.</xnl:NameLine><xnl:FirstName>Teuntje</xnl:FirstName><xnl:NamePrefix></xnl:NamePrefix><xnl:LastName>Berkhout</xnl:LastName></xnl:PersonName></CandidateFullName><Gender>female</Gender><QualifyingAddress><xal:Locality><xal:LocalityName>Best</xal:LocalityName></xal:Locality></QualifyingAddress></Candidate><Ranking>1</Ranking><Elected>yes</Elected></Selection><Selection><Candidate><CandidateIdentifier Id="3"></CandidateIdentifier><CandidateFullName><xnl:PersonName><xnl:NameLine NameType="Initials">A.B.</xnl:NameLine><xnl:FirstName>Stan</xnl:FirstName><xnl:NamePrefix>van der</xnl:NamePrefix><xnl:LastName>Heijden</xnl:LastName></xnl:PersonName></CandidateFullName><Gender>male</Gender><QualifyingAddress><xal:Locality><xal:LocalityName>Best</xal:LocalityName></xal:Locality></QualifyingAddress></Candidate><Ranking>1</Ranking><Elected>yes</Elected></Selection><Selection><Candidate><CandidateIdentifier Id="4"></CandidateIdentifier><CandidateFullName><xnl:PersonName><xnl:NameLine NameType="Initials">R.F.C.</xnl:NameLine><xnl:FirstName>Rob</xnl:FirstName><xnl:NamePrefix></xnl:NamePrefix><xnl:LastName>Snellen</xnl:LastName></xnl:PersonName></CandidateFullName><Gender>male</Gender><QualifyingAddress><xal:Locality><xal:LocalityName>Best</xal:LocalityName></xal:Locality></QualifyingAddress></Candidate><Ranking>2</Ranking><Elected>yes</Elected></Selection><Selection><AffiliationIdentifier Id="5"><RegisteredName>D66</RegisteredName></AffiliationIdentifier><Elected>yes</Elected></Selection><Selection><Candidate><CandidateIdentifier Id="1"></CandidateIdentifier><CandidateFullName><xnl:PersonName><xnl:NameLine NameType="Initials">M.L.N</xnl:NameLine><xnl:FirstName>Marius</xnl:FirstName><xnl:NamePrefix></xnl:NamePrefix><xnl:LastName>Ekamp</xnl:LastName></xnl:PersonName></CandidateFullName><QualifyingAddress><xal:Locality><xal:LocalityName>Best</xal:LocalityName></xal:Locality></QualifyingAddress></Candidate><Ranking>1</Ranking><Elected>yes</Elected></Selection><Selection><Candidate><CandidateIdentifier Id="2"></CandidateIdentifier><CandidateFullName><xnl:PersonName><xnl:NameLine NameType="Initials">M.A.J.</xnl:NameLine><xnl:FirstName>Marlie</xnl:FirstName><xnl:NamePrefix></xnl:NamePrefix><xnl:LastName>Bongaerts</xnl:LastName></xnl:PersonName></CandidateFullName><QualifyingAddress><xal:Locality><xal:LocalityName>Best</xal:LocalityName></xal:Locality></QualifyingAddress></Candidate><Ranking>1</Ranking><Elected>yes</Elected></Selection><Selection><Candidate><CandidateIdentifier Id="3"></CandidateIdentifier><CandidateFullName><xnl:PersonName><xnl:NameLine NameType="Initials">S.H.F.</xnl:NameLine><xnl:FirstName>Sjoerd</xnl:FirstName><xnl:NamePrefix></xnl:NamePrefix><xnl:LastName>Vrijburg</xnl:LastName></xnl:PersonName></CandidateFullName><QualifyingAddress><xal:Locality><xal:LocalityName>Best</xal:LocalityName></xal:Locality></QualifyingAddress></Candidate><Ranking>1</Ranking><Elected>yes</Elected></Selection><Selection><Candidate><CandidateIdentifier Id="4"></CandidateIdentifier><CandidateFullName><xnl:PersonName><xnl:NameLine NameType="Initials">P.T.H.M.</xnl:NameLine><xnl:FirstName>Pieter</xnl:FirstName><xnl:NamePrefix></xnl:NamePrefix><xnl:LastName>Meeuwis</xnl:LastName></xnl:PersonName></CandidateFullName><QualifyingAddress><xal:Locality><xal:LocalityName>Best</xal:LocalityName></xal:Locality></QualifyingAddress></Candidate><Ranking>1</Ranking><Elected>yes</Elected></Selection><Selection><AffiliationIdentifier Id="6"><RegisteredName>Gemeentebelangen Best</RegisteredName></AffiliationIdentifier><Elected>yes</Elected></Selection><Selection><Candidate><CandidateIdentifier Id="1"></CandidateIdentifier><CandidateFullName><xnl:PersonName><xnl:NameLine NameType="Initials">D.J.A.</xnl:NameLine><xnl:FirstName>Diana</xnl:FirstName><xnl:NamePrefix>van</xnl:NamePrefix><xnl:LastName>Weert - van Geffen</xnl:LastName></xnl:PersonName></CandidateFullName><Gender>female</Gender><QualifyingAddress><xal:Locality><xal:LocalityName>Best</xal:LocalityName></xal:Locality></QualifyingAddress></Candidate><Ranking>1</Ranking><Elected>yes</Elected></Selection><Selection><AffiliationIdentifier Id="7"><RegisteredName>Partij van de Arbeid (P.v.d.A.) / GROENLINKS</RegisteredName></AffiliationIdentifier><Elected>yes</Elected></Selection><Selection><Candidate><CandidateIdentifier Id="1"></CandidateIdentifier><CandidateFullName><xnl:PersonName><xnl:NameLine NameType="Initials">R.</xnl:NameLine><xnl:FirstName>Rob</xnl:FirstName><xnl:NamePrefix></xnl:NamePrefix><xnl:LastName>Vader</xnl:LastName></xnl:PersonName></CandidateFullName><Gender>male</Gender><QualifyingAddress><xal:Locality><xal:LocalityName>Best</xal:LocalityName></xal:Locality></QualifyingAddress></Candidate><Ranking>1</Ranking><Elected>yes</Elected></Selection><Selection><Candidate><CandidateIdentifier Id="2"></CandidateIdentifier><CandidateFullName><xnl:PersonName><xnl:NameLine NameType="Initials">E.L.H.</xnl:NameLine><xnl:FirstName>Evi</xnl:FirstName><xnl:NamePrefix></xnl:NamePrefix><xnl:LastName>Thijssen</xnl:LastName></xnl:PersonName></CandidateFullName><Gender>female</Gender><QualifyingAddress><xal:Locality><xal:LocalityName>Best</xal:LocalityName></xal:Locality></QualifyingAddress></Candidate><Ranking>1</Ranking><Elected>yes</Elected></Selection><Selection><Candidate><CandidateIdentifier Id="3"></CandidateIdentifier><CandidateFullName><xnl:PersonName><xnl:NameLine NameType="Initials">S.D.M.</xnl:NameLine><xnl:FirstName>Sanne</xnl:FirstName><xnl:NamePrefix>de</xnl:NamePrefix><xnl:LastName>Bie</xnl:LastName></xnl:PersonName></CandidateFullName><Gender>female</Gender><QualifyingAddress><xal:Locality><xal:LocalityName>Best</xal:LocalityName></xal:Locality></QualifyingAddress></Candidate><Ranking>1</Ranking><Elected>yes</Elected></Selection><Selection><AffiliationIdentifier Id="8"><RegisteredName>ChristenUnie</RegisteredName></AffiliationIdentifier><Elected>yes</Elected></Selection><Selection><Candidate><CandidateIdentifier Id="1"></CandidateIdentifier><CandidateFullName><xnl:PersonName><xnl:NameLine NameType="Initials">W.</xnl:NameLine><xnl:FirstName>Wouter</xnl:FirstName><xnl:NamePrefix></xnl:NamePrefix><xnl:LastName>Bondt</xnl:LastName></xnl:PersonName></CandidateFullName><Gender>male</Gender><QualifyingAddress><xal:Locality><xal:LocalityName>Best</xal:LocalityName></xal:Locality></QualifyingAddress></Candidate><Ranking>1</Ranking><Elected>yes</Elected></Selection></Contest></Election></Result></EML>